cocotbextPlotData/README.md
cocotbextPlotData/__init__.py
cocotbextPlotData/plotData.py
cocotbextPlotData/sarasa-mono-sc-regular.ttf
cocotbextPlotData-0.1.dist-info/METADATA
cocotbextPlotData-0.1.dist-info/WHEEL
cocotbextPlotData-0.1.dist-info/top_level.txt
cocotbextPlotData-0.1.dist-info/RECORD
